healthtrends
