Metadata-Version: 1.0
Name: gtrends-tools
Version: 1.0
Summary: Interface for retrieving data from Google Health Trends API
Home-page: https://github.com/fl16180/gtrends-tools
Author: Fred Lu
Author-email: fredlu.flac@gmail.com
License: MIT
Platform: UNKNOWN
